access2thematrix/__init__.py
access2thematrix/access2thematrix.py
access2thematrix/pkg_info.py
access2theMatrix-0.4.4.dist-info/LICENSE.txt
access2theMatrix-0.4.4.dist-info/METADATA
access2theMatrix-0.4.4.dist-info/WHEEL
access2theMatrix-0.4.4.dist-info/top_level.txt
access2theMatrix-0.4.4.dist-info/RECORD
