Metadata-Version: 2.1
Name: access2theMatrix
Version: 0.4.4
Summary: Scienta Omicron (NanoScience) (NanoTechnology) MATRIX Control System result file accessing tool
Author: Stephan Zevenhuizen
Author-email: S.J.M.Zevenhuizen@uu.nl
License: BSD License
Keywords: SPM scanning probe microscopy image analysis
Classifier: Development Status :: 5 - Production/Stable
Classifier: Intended Audience :: Science/Research
Classifier: License :: OSI Approved :: BSD License
Classifier: Natural Language :: English
Classifier: Operating System :: OS Independent
Classifier: Programming Language :: Python :: 2
Classifier: Programming Language :: Python :: 3
Classifier: Topic :: Scientific/Engineering :: Chemistry
Classifier: Topic :: Scientific/Engineering :: Information Analysis
Classifier: Topic :: Scientific/Engineering :: Physics
Classifier: Topic :: Software Development :: Libraries :: Python Modules
Requires-Python: >=2.7, !=3.0.*, !=3.1.*, !=3.2.*, <4
License-File: LICENSE.txt
Requires-Dist: numpy
Requires-Dist: six
